pymb/__init__.py
pymb/bst.py
pymb/graph.py
pymb/hashtable.py
pymb/linkedlist.py
pymb/matrix.py
pymb/queue.py
pymb/sortedlinkedlist.py
pymb/stack.py
pymb/vector.py
pymb/basetypes/__init__.py
pymb/basetypes/abstractlist.py
pymb/basetypes/node.py
pymbdata-0.0.1.dist-info/LICENSE
pymbdata-0.0.1.dist-info/METADATA
pymbdata-0.0.1.dist-info/WHEEL
pymbdata-0.0.1.dist-info/top_level.txt
pymbdata-0.0.1.dist-info/RECORD
