Metadata-Version: 2.1
Name: pymbdata
Version: 0.0.1
Summary: A small example package
Home-page: https://github.com/gamirou/pymbdata
Author: George Sima
License: UNKNOWN
Platform: UNKNOWN
Classifier: Programming Language :: Python :: 3
Classifier: License :: OSI Approved :: MIT License
Classifier: Operating System :: OS Independent
Classifier: Development Status :: 1 - Planning
Classifier: Intended Audience :: Developers
Requires-Dist: numpy
